<?xml version="1.0" encoding="UTF-8"?>

<databaseChangeLog
        xmlns="http://www.liquibase.org/xml/ns/dbchangelog"
        xmlns:xsi="http://www.w3.org/2001/XMLSchema-instance"
        xsi:schemaLocation="http://www.liquibase.org/xml/ns/dbchangelog
         http://www.liquibase.org/xml/ns/dbchangelog/dbchangelog-3.1.xsd">

    <include file="changelog/initial-schema-document.xml" relativeToChangelogFile="true"/>
    <include file="changelog/initial-schema-document-post.xml" relativeToChangelogFile="true"/>
    <include file="changelog/initial-schema-event.xml" relativeToChangelogFile="true"/>
    <include file="changelog/initial-schema-event-user.xml" relativeToChangelogFile="true"/>
    <include file="changelog/initial-schema-group.xml" relativeToChangelogFile="true"/>
    <include file="changelog/initial-schema-notification.xml" relativeToChangelogFile="true"/>
    <include file="changelog/initial-schema-post.xml" relativeToChangelogFile="true"/>
    <include file="changelog/initial-schema-request.xml" relativeToChangelogFile="true"/>
    <include file="changelog/initial-schema-role.xml" relativeToChangelogFile="true"/>
    <include file="changelog/drop-table-destination.xml" relativeToChangelogFile="true"/>
    <include file="changelog/drop-table-user-destination.xml" relativeToChangelogFile="true"/>
    <include file="changelog/initial-schema-user-notification.xml" relativeToChangelogFile="true"/>
    <include file="changelog/initial-schema-user-role.xml" relativeToChangelogFile="true"/>
    <include file="changelog/initial-schema-users.xml" relativeToChangelogFile="true"/>
    <include file="changelog/initial-foreign-keys.xml" relativeToChangelogFile="true"/>
</databaseChangeLog>